siwe_auth/__init__.py
flask_siwe_auth-0.1.0.dist-info/WHEEL
flask_siwe_auth-0.1.0.dist-info/METADATA
flask_siwe_auth-0.1.0.dist-info/RECORD
